CHANGELOG.txt
LICENSE.txt
MANIFEST.in
README.txt
setup.py
moreFunctions/__init__.py
moreFunctions.egg-info/PKG-INFO
moreFunctions.egg-info/SOURCES.txt
moreFunctions.egg-info/dependency_links.txt
moreFunctions.egg-info/top_level.txt